mkdocs_smart_meta_plugin/__init__.py
mkdocs_smart_meta_plugin/plugin.py
mkdocs_smart_meta_plugin-0.1.0.dist-info/METADATA
mkdocs_smart_meta_plugin-0.1.0.dist-info/WHEEL
mkdocs_smart_meta_plugin-0.1.0.dist-info/entry_points.txt
mkdocs_smart_meta_plugin-0.1.0.dist-info/top_level.txt
mkdocs_smart_meta_plugin-0.1.0.dist-info/RECORD
