Metadata-Version: 2.1
Name: mkdocs-smart-meta-plugin
Version: 0.1.0
Summary: Generates meta tags for MkDocs automatically
Home-page: https://github.com/aprosvetova/mkdocs-smart-meta-plugin
Author: Anna Prosvetova
Author-email: anna@prosvetova.me
License: MIT
Keywords: mkdocs
Platform: UNKNOWN
Requires-Python: >=3.7
Requires-Dist: mkdocs (>=1.1)
Requires-Dist: beautifulsoup4
